{
  "model":"Collection<io.alkapivo.visu.service.subtitle.SubtitleTemplate>",
  "data":{
    "subtitle_alkapivo":{
      "lines":[
        "Alkapivo",
        "2025"
      ]
    },
    "subtitle_sewerslvt_psychosis":{
      "lines":[
        "",
        "Psychosis"
      ]
    },
    "subtitle_sewerslvt":{
      "lines":[
        "Sewerslvt",
        ""
      ]
    },
    "subtitle_schnoopy_destination_unknown":{
      "lines":[
        "",
        "Destination Unknown"
      ]
    },
    "subtitle_schnoopy":{
      "lines":[
        "Schnoopy",
        ""
      ]
    }
  },
  "version":"1"
}