{
  "version": "1",
  "model": "Collection<io.alkapivo.visu.ui.VisuMenuNode>",
  "data": {
    "root.tracks": {
      "title": "Select track",
      "back": "root",
      "entries": [
        {
          "name": "digitalshadow",
          "title": "Zoogies",
          "event": {
            "type": "open-track-setup",
            "data": {
              "path": "track/Zoogies/Singles/digitalshadow/manifest.visu",
              "node": "root.tracks"
            }
          }
        },
        {
          "name": "Just To Create Something",
          "title": "kedy_selma",
          "event": {
            "type": "open-track-setup",
            "data": {
              "path": "track/kedy_selma/Just-To-Create-Something/Just-To-Create-Something/manifest.visu",
              "node": "root.tracks"
            }
          }
        },
        {
          "name": "Passion",
          "title": "kedy_selma",
          "event": {
            "type": "open-track-setup",
            "data": {
              "path": "track/kedy_selma/Singles/Passion/manifest.visu",
              "node": "root.tracks"
            }
          }
        },
        {
          "name": "the memories fade but the feeling remains",
          "title": "pikaro & PAXNKOXD",
          "event": {
            "type": "open-track-setup",
            "data": {
              "path": "track/pikaro/Singles/the-memories-fade-but-the-feeling-remains/manifest.visu",
              "node": "root.tracks"
            }
          }
        },
        {
          "name": "Psychosis",
          "title": "Sewerslvt",
          "event": {
            "type": "open-track-setup",
            "data": {
              "path": "track/Sewerslvt/The-World-is-Fvcked/Psychosis/manifest.visu",
              "node": "root.tracks"
            }
          }
        },
        {
          "name": "Create and Yet Fate's Faw Avoid *",
          "title": "GOETIA",
          "event": {
            "type": "open-track-setup",
            "data": {
              "path": "track/GOETIA/Death-of-the-Muse/Create-and-Yet-Fates-Faw-Avoid/manifest.visu",
              "node": "root.tracks"
            }
          }
        },
        {
          "name": "Purple Hearts In Her Eyes",
          "title": "Sewerslvt",
          "event": {
            "type": "open-track-setup",
            "data": {
              "path": "track/Sewerslvt/Skitzofrenia-Simulation/Purple-Hearts-In-Her-Eyes/manifest.visu",
              "node": "root.tracks"
            }
          }
        },
        {
          "name": "Destination Unknown",
          "title": "Schnoopy",
          "event": {
            "type": "open-track-setup",
            "data": {
              "path": "track/Schnoopy/Proxima/Destination-Unknown/manifest.visu",
              "node": "rooty"
            }
          }
        }
      ]
    }
  }
}
